CHANGES.txt
MANIFEST.in
README.txt
setup.py
src/z3c/__init__.py
src/z3c.winpdb.egg-info/PKG-INFO
src/z3c.winpdb.egg-info/SOURCES.txt
src/z3c.winpdb.egg-info/dependency_links.txt
src/z3c.winpdb.egg-info/entry_points.txt
src/z3c.winpdb.egg-info/namespace_packages.txt
src/z3c.winpdb.egg-info/not-zip-safe
src/z3c.winpdb.egg-info/requires.txt
src/z3c.winpdb.egg-info/top_level.txt
src/z3c/winpdb/__init__.py
src/z3c/winpdb/configure.zcml