Metadata-Version: 1.1
Name: z3c.winpdb
Version: 0.1.4
Summary: Enable remote debugging with winpdb in Zope / Plone
Home-page: UNKNOWN
Author: Thomas Schilz
Author-email: thschilz@web.de
License: gpl
Platform: UNKNOWN
Classifier: Programming Language :: Python
